schema_cat/__init__.py
schema_cat/base_provider.py
schema_cat/model_registry.py
schema_cat/model_router.py
schema_cat/prompt.py
schema_cat/provider_enum.py
schema_cat/providers/__init__.py
schema_cat/providers/anthropic_provider.py
schema_cat/providers/comet_provider.py
schema_cat/providers/openai_compat_provider.py
schema_cat/providers/openai_provider.py
schema_cat/providers/openrouter_provider.py
schema_cat/retry.py
schema_cat/schema.py
schema_cat/xml.py
schema_cat-0.2.4.dist-info/METADATA
schema_cat-0.2.4.dist-info/WHEEL
schema_cat-0.2.4.dist-info/entry_points.txt
schema_cat-0.2.4.dist-info/RECORD
