Metadata-Version: 2.3
Name: schema-cat
Version: 0.2.4
Summary: A Python library for typed prompts
License: MIT
Author: Michael Lahr
Author-email: michael.lahr@gmail.com
Requires-Python: >=3.12
Classifier: License :: OSI Approved :: MIT License
Classifier: Programming Language :: Python :: 3
Classifier: Programming Language :: Python :: 3.12
Classifier: Programming Language :: Python :: 3.13
Requires-Dist: anthropic (>=0.56.0,<0.57.0)
Requires-Dist: bs4 (>=0.0.2,<0.0.3)
Requires-Dist: lxml (>=6.0.0,<7.0.0)
Requires-Dist: openai (>=1.93.0,<2.0.0)
Requires-Dist: pydantic (>=2.11.7,<3.0.0)
Requires-Dist: python-dotenv (>=1.1.1,<2.0.0)
Requires-Dist: pyyaml (>=6.0.2,<7.0.0)
